README.md
pyproject.toml
setup.py
src/analytic_workspace_client.egg-info/PKG-INFO
src/analytic_workspace_client.egg-info/SOURCES.txt
src/analytic_workspace_client.egg-info/dependency_links.txt
src/analytic_workspace_client.egg-info/requires.txt
src/analytic_workspace_client.egg-info/top_level.txt
src/aw_client/__init__.py
src/aw_client/cache.py
src/aw_client/domain.py
src/aw_client/exceptions.py
src/aw_client/session.py
src/aw_client/tools.py
src/aw_client/core/__init__.py
src/aw_client/core/bundle.py
src/aw_client/core/compiler.py
src/aw_client/core/model_vault.py
src/aw_client/core/spark.py
src/aw_client/data_master/__init__.py
src/aw_client/data_master/base.py
src/aw_client/data_master/v0.py
src/aw_client/data_master/v1.py
src/aw_client/data_master/v2.py
src/aw_client/etl_blocks/__init__.py
src/aw_client/etl_blocks/application.py
src/aw_client/etl_blocks/dto.py
src/aw_client/etl_blocks/runtime.py
src/aw_client/etl_blocks/services.py
src/aw_client/etl_blocks/test_data.py
src/aw_client/etl_blocks/tools.py
src/aw_client/ml/__init__.py
src/aw_client/ml/mlflow_wrapper.py
src/aw_client/model_dev/__init__.py
src/aw_client/model_dev/application.py
src/aw_client/model_dev/cache.py
src/aw_client/model_dev/runner.py
src/aw_client/model_dev/virtual_objects.py
src/aw_client/models/__init__.py
src/aw_client/models/model_schema.py
src/aw_etl/__init__.py
src/aw_etl/compiler.py
src/aw_etl/etl_blocks.py
src/aw_etl/models.py