Metadata-Version: 2.1
Name: analytic-workspace-client
Version: 1.33.0
Summary: Библиотека для подключения к Analytic Workspace
Home-page: https://analyticworkspace.ru/
Author: Analytic Workspace
Author-email: aw_help@analyticworkspace.ru
License: UNKNOWN
Platform: UNKNOWN
Classifier: Programming Language :: Python :: 3
Classifier: License :: OSI Approved :: MIT License
Classifier: Operating System :: OS Independent
Requires-Python: >=3.10,<4
Provides-Extra: dev
Provides-Extra: ml
